{"cameraMode":{"drawMode":0,"name":"Shaded","section":"Shading Mode"},"sceneLighting":true,"audioPlay":false,"sceneViewState":{"m_AlwaysRefresh":false,"showFog":true,"showSkybox":true,"showFlares":true,"showImageEffects":true,"showParticleSystems":true,"showVisualEffectGraphs":true,"m_FxEnabled":true},"in2DMode":false,"pivot":{"x":2.687718391418457,"y":-1.8297119140625,"z":-0.9537973403930664},"rotation":{"x":-0.08662442862987519,"y":0.9127997159957886,"z":-0.2647636830806732,"w":-0.2986462414264679},"size":10.0,"orthographic":false}